{
  "name": "Aletheia",
  "description": "\nAletheia\n\n\n\t\n\t\t\n\t\t\n\t\n\t\n\n\n\tBiographical Information\n\n\n\t\n\t\tAlias\n\t\n\tOracle of Delphi\n\n\n\n\t\n\t\tBirthplace\n\t\n\tDelphi\n\n\n\n\t\n\t\tDeathplace\n\t\n\tThe Oracle's Chambers\n\n\n\n\t\n\t\tLocation\n\t\n\tThe Oracle's Chambers\n\n\n\n\t\n\t\tAge\n\t\n\tUnknown (old age)\n\n\n\n\t\n\t\tNationality\n\t\n\t Greek\n\n\n\n\t\n\t\tStatus\n\t\n\tDeceased (Fatally wounded by falling which caused by Pollux)\n\n\n\n\n\tPhysical Information\n\n\n\t\n\t\tRace\n\t\n\tMortal\n\n\n\n\t\n\t\tGender\n\t\n\tFemale\n\n\n\n\n\tRelationship Information\n\n\n\t\n\t\tFamily\n\t\n\tOrkos (lover)\n\n\n\n\n\tBehind the Scenes\n\n\n\t\n\t\tVoiced by\n\t\n\tAdrienne Barbeau\n\n\n\n\t\n\t\tAppears in\n\t\n\tGod of War: Ascension  God of War Ragnarök (mentioned only)\n\n\nAletheia\nἀλήθεια\nDelphi\nKratos\nquest\nAres\nthe Furies",
  "image": "https://static.wikia.nocookie.net/godofwar/images/0/03/Aletheia.png/revision/latest/scale-to-width-down/268?cb=20130518080146",
  "biographicalInformation": {
    "birthplace": "Delphi",
    "deathplace": "The Oracle's Chambers",
    "location": "The Oracle's Chambers",
    "age": "Unknown (old age)",
    "nationality": "Greek",
    "status": "Deceased (Fatally wounded by falling which caused by Pollux)"
  },
  "physicalInformation": {
    "race": "Mortal",
    "gender": "Female"
  },
  "wiki": "https://godofwar.fandom.com/wiki/Aletheia"
}