{
  "name": "Aphrodite's Handmaidens",
  "description": "\nAphrodite's Handmaidens\n\n\n\t\n\t\t\n\t\t\n\t\n\t\n\n\n\tBiographical Information\n\n\n\t\n\t\tAlias\n\t\n\tAphrodite's Handmaidens\n\n\n\n\t\n\t\tLocation\n\t\n\tAphrodite's Chamber\n\n\n\n\t\n\t\tStatus\n\t\n\tUnknown\n\n\n\n\n\tPhysical Information\n\n\n\t\n\t\tRace\n\t\n\tMortal\n\n\n\n\t\n\t\tGender\n\t\n\tFemale\n\n\n\n\t\n\t\tHair Colour\n\t\n\tBlonde (white)Black (brown)\n\n\n\n\t\n\t\tHair Style\n\t\n\tShoulder length\n\n\n\n\t\n\t\tHair Type\n\t\n\tStraight\n\n\n\n\t\n\t\tEyebrow Color\n\t\n\tBlonde (white)Brunette (brown)\n\n\n\n\t\n\t\tEye Colour\n\t\n\tGreen (white)Brown (brown)\n\n\n\n\t\n\t\tSkin Colour\n\t\n\tLight (white)Dark (brown)\n\n\n\n\n\tRelationship Information\n\n\n\t\n\t\tLoyalties\n\t\n\tAphrodite (mistress/lover)Kratos\n\n\n\n\t\n\t\tOccupation\n\t\n\tServants of Aphrodite\n\n\n\n\t\n\t\tHobby\n\t\n\tBeing with Aphrodite Having intercourse with Aphrodite and each other\n\n\n\n\t\n\t\tPersonality\n\t\n\tCare-freePleasure driven\n\n\n\n\n\tBehind the Scenes\n\n\n\t\n\t\tVoiced by\n\t\n\tHolly Fields (Dark one)Erin Mathews (White one)\n\n\n\n\t\n\t\tAppears in\n\t\n\tGod of War III\nAphrodite's Handmaidens\nAphrodite\n",
  "image": "https://static.wikia.nocookie.net/godofwar/images/a/a9/Screweyefaiuk.png/revision/latest/scale-to-width-down/268?cb=20240128183657",
  "biographicalInformation": {
    "location": "Aphrodite's Chamber",
    "status": "Unknown"
  },
  "physicalInformation": {
    "race": "Mortal",
    "gender": "Female",
    "hair_colour": [
      "Blonde (white)",
      "Black (brown)"
    ],
    "hair_style": "Shoulder length",
    "eyebrow_color": [
      "Blonde (white)",
      "Brunette (brown)"
    ],
    "skin_colour": [
      "Light (white)",
      "Dark (brown)"
    ]
  },
  "wiki": "https://godofwar.fandom.com/wiki/Aphrodite%27s_Handmaidens"
}