{
  "name": "Erinys",
  "description": "\nErinys\n\n\n\t\n\t\t\n\t\t\n\t\n\t\n\n\n\tBiographical Information\n\n\n\t\n\t\tTitles\n\t\n\tGoddess of VengenceGoddess of Death\n\n\n\n\t\n\t\tAlias\n\t\n\tDaughter of DeathMessenger of Thanatos\n\n\n\n\t\n\t\tBirthplace\n\t\n\tDomain of Death\n\n\n\n\t\n\t\tDeathplace\n\t\n\tNear of Sparta\n\n\n\n\t\n\t\tStatus\n\t\n\tDeceased (Stabbed in the back by Kratos with the Blades of Athena)\n\n\n\n\n\tPhysical Information\n\n\n\t\n\t\tRace\n\t\n\tGoddess\n\n\n\n\t\n\t\tGender\n\t\n\tFemale\n\n\n\n\t\n\t\tHair Colour\n\t\n\tBlack\n\n\n\n\t\n\t\tEye Colour\n\t\n\tBlack\n\n\n\n\t\n\t\tSkin Colour\n\t\n\tGrey\n\n\n\n\n\tRelationship Information\n\n\n\t\n\t\tFamily\n\t\n\tChaos (Ancestor)Erebus (Grandfather)Nyx (Grandmother)Ouranos (Granduncle) †Gaia (Grandaunt/Mother) †Tartarus (Granduncle)Eros (Granduncle)The Furies (Grandaunts) †Thanatos (Father) †Morpheus (Uncle)Charon (Uncle) †Nemesis (Aunt)Sisters of Fate  (Aunts)Cronos (First Cousin Once Removed) †Rhea (First Cousin Once Removed)Oceanus (First Cousin Once Removed) †Tethys (First Cousin Once Removed)Hyperion (First Cousin Once Removed) †Theia (First Cousin Once Removed)Coeus (First Cousin Once Removed)Phoebe (First Cousin Once Removed)Crius (First Cousin Once Removed)Themis (First Cousin Once Removed)Iapetus (First Cousin Once Removed)Mnemosyne (First Cousin Once Removed)Typhon (First Cousin Once Removed)Thera (First Cousin Once Removed)Gyges (First Cousin Once Removed) †Aegaeon (First Cousin Once Removed) †Cottus (First Cousin Once Removed) †Hestia (Second Cousin)Demeter (Second Cousin)Hera (Second Cousin) †Hades (Second Cousin) †Poseidon (Second Cousin) †Zeus (Second Cousin) †Amphitrite (Second Cousin)Helios (Second Cousin) †Selene (Second Cousin)Eos (Second Cousin) †Perses (Second Cousin) †Atlas (Second Cousin/Second Cousin Once Removed)Prometheus (Second Cousin/Second Cousin Once Removed) †Epimetheus (Second Cousin/Second Cousin Once Removed) †Triton (Second Cousin Once Removed)Polyphemus (Second Cousin Once Removed) †Pegasus (Second Cousin Once Removed)†Theseus (Second Cousin Once Removed) †Pelias (Second Cousin Once Removed)Nyads (Second Cousins Once Removed)Athena (Second Cousin Once Removed) †Ares (Second Cousin Once Removed) †Hephaestus (Second Cousin Once Removed) †Persephone (Second Cousin Once Removed) †Zagreus (Second Cousin Once Removed) †Aphrodite (Second Cousin Once Removed)Artemis (Second Cousin Once Removed)Apollo (Second Cousin Once Removed)Hermes (Second Cousin Once Removed/Second Cousin Twice Removed/Second Cousin Thrice Removed) †Muses (Second Cousins Once Removed/Second Cousins)Dionysus (Second Cousin Once Removed)Aecus (Second Cousin Once Removed) †Minos (Second Cousin Once Removed) †Rhadamanthus (Second Cousin Once Removed) †Pollux (Second Cousin Once Removed) †Peirithous (Second Cousin Once Removed) †Perseus (Second Cousin Once Removed) †Hercules (Second Cousin Once Removed) †Kratos (Second Cousin Once Removed)Deimos (Second Cousin Once Removed) †Aeëtes (Second Cousin Once Removed)Circe (Second Cousin Once Removed)Boreas (Second Cousin Once Removed) †Nike (Second Cousin Once Removed)Phobos (Second Cousin Twice Removed)Orkos (Second Cousin Twice Removed/First Cousin Once Removed) †Pandora (Adoptive Second Cousin Twice Removed) †Zora and Lora (Second Cousins Twice Removed)Asclepius (Second Cousin Twice Removed)Ceryx (Second Cousin Twice Removed/Second Cousin Thrice Removed/Second Cousin Four Times Removed) †Ariadne (Second Cousin Twice Removed)Calliope (Second Cousin Twice Removed) †Atreus (Second Cousin Twice Removed)Medea (Second Cousin Twice Removed)Jason (Second Cousin Four Times Removed/Second Cousin Five Times Removed/Second Cousin Six Times Removed) †\n\n\n\n\t\n\t\tLoyalties\n\t\n\tThanatos\n\n\n\n\t\n\t\tEnemies\n\t\n\tKratos (killer)\n\n\n\n\t\n\t\tVictims\n\t\n\tNumerous MortalsDominusThe Soldier With No EyesSlain Spartan\n\n\n\n\n\tEquipment\n\n\n\t\n\t\tPower\n\t\n\tVoid CreatorsSuperhuman SpeedShapeshiftFlightSummoning\n\n\n\n\n\tBehind the Scenes\n\n\n\t\n\t\tVoiced by\n\t\n\tJennifer HaleErin Torpey\n\n\n\n\t\n\t\tAppears in\n\t\n\tGod of War: Ghost of Sparta\n\nErinys (Greek: Ἐρινύς) was the daughter of Thanatos, God of Death, and she served as his messenger. She is the Goddess of Vengeance and Death who serves as the secondary antagonist in God of War: Ghost of Sparta.",
  "image": "https://static.wikia.nocookie.net/godofwar/images/1/14/ErinysImage_23.jpg/revision/latest/scale-to-width-down/268?cb=20101119015333",
  "biographicalInformation": {
    "birthplace": "Domain of Death",
    "deathplace": "Near of Sparta",
    "status": "Deceased (Stabbed in the back by Kratos with the Blades of Athena)"
  },
  "physicalInformation": {
    "race": "Goddess",
    "gender": "Female",
    "hair_colour": "Black",
    "skin_colour": "Grey"
  },
  "wiki": "https://godofwar.fandom.com/wiki/Erinys"
}