{
  "name": "Oracle of Athens",
  "description": "\nOracle of Athens\n\n\n\t\n\t\t\n\t\t\n\t\n\t\n\n\n\tBiographical Information\n\n\n\t\n\t\tBirthplace\n\t\n\tAthens\n\n\n\n\t\n\t\tLocation\n\t\n\tAthens\n\n\n\n\t\n\t\tAge\n\t\n\tAdult\n\n\n\n\t\n\t\tNationality\n\t\n\t Greek\n\n\n\n\t\n\t\tStatus\n\t\n\tAlive (Presumed)\n\n\n\n\n\tPhysical Information\n\n\n\t\n\t\tRace\n\t\n\tMortal\n\n\n\n\t\n\t\tGender\n\t\n\tFemale\n\n\n\n\t\n\t\tHair Colour\n\t\n\tRed\n\n\n\n\t\n\t\tEyebrow Color\n\t\n\tRed\n\n\n\n\t\n\t\tEye Colour\n\t\n\tGrey\n\n\n\n\t\n\t\tSkin Colour\n\t\n\tFair\n\n\n\n\n\tRelationship Information\n\n\n\t\n\t\tLoyalties\n\t\n\tAthensAthena\n\n\n\n\t\n\t\tOccupation\n\t\n\tOracle\n\n\n\n\n\tEquipment\n\n\n\t\n\t\tPower\n\t\n\tForesightWisdomReading memories\n\n\n\n\n\tBehind the Scenes\n\n\n\t\n\t\tVoiced by\n\t\n\tSusanne Blakeslee\n\n\n\n\t\n\t\tAppears in\n\t\n\tGod of War\n\nThe Oracle of Athens is one of the many inhabitants of Athens, and assisted Kratos in his quest to defeat Ares.",
  "image": "https://static.wikia.nocookie.net/godofwar/images/e/eb/OracleofAthens.jpg/revision/latest/scale-to-width-down/268?cb=20080531192947",
  "biographicalInformation": {
    "birthplace": "Athens",
    "location": "Athens",
    "age": "Adult",
    "nationality": "Greek",
    "status": "Alive (Presumed)"
  },
  "physicalInformation": {
    "race": "Mortal",
    "gender": "Female",
    "hair_colour": "Red",
    "eyebrow_color": "Red",
    "skin_colour": "Fair"
  },
  "wiki": "https://godofwar.fandom.com/wiki/Oracle_of_Athens"
}