{
  "name": "Persian King",
  "description": "\nPersian King\n\n\n\t\n\t\t\n\t\t\n\t\n\t\n\n\n\tBiographical Information\n\n\n\t\n\t\tAlias\n\t\n\tKing of Persia  Greek Slayer\n\n\n\n\t\n\t\tBirthplace\n\t\n\tPersia\n\n\n\n\t\n\t\tDeathplace\n\t\n\tAttica\n\n\n\n\t\n\t\tLocation\n\t\n\tPersia\n\n\n\n\t\n\t\tCitizenship\n\t\n\tPersian\n\n\n\n\t\n\t\tNationality\n\t\n\tPersian\n\n\n\n\t\n\t\tStatus\n\t\n\tDeceased (Face smashed by Kratos with a box)\n\n\n\n\n\tPhysical Information\n\n\n\t\n\t\tRace\n\t\n\tMortal\n\n\n\n\t\n\t\tGender\n\t\n\tMale\n\n\n\n\t\n\t\tHair Colour\n\t\n\tBrown\n\n\n\n\t\n\t\tEyebrow Color\n\t\n\tBrown\n\n\n\n\t\n\t\tEye Colour\n\t\n\tWhite (Left)Brown (Rigth)\n\n\n\n\t\n\t\tBeard Color\n\t\n\tBrown\n\n\n\n\t\n\t\tSkin Colour\n\t\n\tFair\n\n\n\n\n\tRelationship Information\n\n\n\t\n\t\tLoyalties\n\t\n\tHimselfPersia\n\n\n\n\t\n\t\tEnemies\n\t\n\tAtticaKratos\n\n\n\n\t\n\t\tOccupation\n\t\n\tRuler of Persia\n\n\n\n\t\n\t\tVictims\n\t\n\tNumerous Mortals\n\n\n\n\t\n\t\tPets\n\t\n\tBasilisk\n\n\n\n\t\n\t\tGoals\n\t\n\tConquer Attica (Failed)\n\n\n\n\t\n\t\tPersonality\n\t\n\tEvilProud\n\n\n\n\n\tEquipment\n\n\n\t\n\t\tWeapon\n\t\n\tScimitarPeltarion\n\n\n\n\t\n\t\tPower\n\t\n\tSuperhuman StrengthPyrokinesisEfreet Summon\n\n\n\n\t\n\t\tItem\n\t\n\tLamp of Efreet\n\n\n\n\n\tBehind the Scenes\n\n\n\t\n\t\tVoiced by\n\t\n\tFred Tatasciore\n\n\n\n\t\n\t\tAppears in\n\t\n\tGod of War: Chains of Olympus\n\nThe Persian King is the man who led the massive siege upon Attica using many men and a basilisk to bring Greece down by the Persian Empire. He is the first boss you encounter in the game.",
  "image": "https://static.wikia.nocookie.net/godofwar/images/b/ba/Persian_King_2.jpg/revision/latest/scale-to-width-down/268?cb=20080714214555",
  "biographicalInformation": {
    "birthplace": "Persia",
    "deathplace": "Attica",
    "location": "Persia",
    "citizenship": "Persian",
    "nationality": "Persian",
    "status": "Deceased (Face smashed by Kratos with a box)"
  },
  "physicalInformation": {
    "race": "Mortal",
    "gender": "Male",
    "hair_colour": "Brown",
    "eyebrow_color": "Brown",
    "beard_color": "Brown",
    "skin_colour": "Fair"
  },
  "wiki": "https://godofwar.fandom.com/wiki/Persian_King"
}