{
  "name": "Stheno",
  "description": "\nStheno\n\n\n\t\n\t\t\n\t\t\n\t\n\t\n\n\n\tBiographical Information\n\n\n\t\n\t\tBirthplace\n\t\n\tCaverns beneath Mount Olympus\n\n\n\n\t\n\t\tLocation\n\t\n\tBog of the Forgotten (Multiplayer)\n\n\n\n\t\n\t\tStatus\n\t\n\tAlive (Possible)\n\n\n\n\n\tPhysical Information\n\n\n\t\n\t\tRace\n\t\n\tGorgon  Human (formerly)\n\n\n\n\t\n\t\tGender\n\t\n\tFemale\n\n\n\n\n\tRelationship Information\n\n\n\t\n\t\tFamily\n\t\n\tCeto (Mother)Phorcys (Father)Medusa (Sister) †Euryale (Sister)†Pegasus (Nephew)Charybdis (sister)Scylla (Sister) †Siren (Sisters) †\n\n\n\n\n\tBehind the Scenes\n\n\n\t\n\t\tVoiced by\n\t\n\tNone\n\n\n\n\t\n\t\tAppears in\n\t\n\tGod of War: Ascension (in multiplayer only)\nStheno\nGorgon\nBog of the Forgotten\nGod of War: Ascension's\nmultiplayer\nGorgon Temple\n",
  "image": "https://static.wikia.nocookie.net/godofwar/images/d/d2/Sthenoprint.jpg/revision/latest?cb=20140619032306",
  "biographicalInformation": {
    "birthplace": "Caverns beneath Mount Olympus",
    "location": "Bog of the Forgotten (Multiplayer)",
    "status": "Alive (Possible)"
  },
  "physicalInformation": {
    "race": "Gorgon  Human (formerly)",
    "gender": "Female"
  },
  "wiki": "https://godofwar.fandom.com/wiki/Stheno"
}