{
  "name": "Thera",
  "description": "\nThera\n\n\n\t\n\t\t\n\t\t\n\t\n\t\n\n\n\tBiographical Information\n\n\n\t\n\t\tTitles\n\t\n\tGoddess of VolcanoesGoddess of Lava\n\n\n\n\t\n\t\tAlias\n\t\n\tThira\n\n\n\n\t\n\t\tBirthplace\n\t\n\tIsland of Creation\n\n\n\n\t\n\t\tLocation\n\t\n\tMethana Volcano outside of Atlantis\n\n\n\n\t\n\t\tStatus\n\t\n\tUnknown\n\n\n\n\n\tPhysical Information\n\n\n\t\n\t\tRace\n\t\n\tGod (Titan)\n\n\n\n\t\n\t\tGender\n\t\n\tFemale\n\n\n\n\t\n\t\tHair Colour\n\t\n\tNone\n\n\n\n\t\n\t\tEye Colour\n\t\n\tRed\n\n\n\n\t\n\t\tSkin Colour\n\t\n\tBlack\n\n\n\n\n\tRelationship Information\n\n\n\t\n\t\tFamily\n\t\n\tChaos (Ancestor)Ouranos (Father) †Gaia (Mother) †Erebus (Uncle)Nyx (Aunt)Tartarus (Uncle)Eros (Uncle)The Furies (Aunts) †Cronos (Brother) †Rhea (Sister)Oceanus (Brother) †Tethys (Sister)Hyperion (Brother) †Theia (Sister)Coeus (Brother)Phoebe (Sister)Crius (Brother)Themis (Sister)Iapetus (Brother)Mnemosyne (Sister)Typhon (Half-Brother)Gyges (Brother) †Aegaeon (Brother) †Cottus (Brother) †Hestia (Niece)Demeter (Niece)Hera (Niece) †Hades (Nephew) †Poseidon (Nephew) †Zeus (Nephew) †Amphitrite (Niece)Helios (Nephew) †Selene (Niece)Eos (Niece) †Perses (Nephew) †Atlas (Nephew)Prometheus (Nephew) †Epimetheus (Nephew) †Triton (Grandnephew)Polyphemus (Grandnephew) †Pegasus (Grandnephew)†Theseus (Grandnephew) †Pelias (Grandnephew)Nyads (Grandnieces)Athena (Grandniece) †Ares (Grandnephew) †Hephaestus (Grandnephew) †Persephone (Grandniece/Niece-in-Law) †Zagreus (Grandnephew) †Aphrodite (Grandniece)Artemis (Grandniece)Apollo (Grandnephew)Hermes (Grandnephew/Great-Grandnephew/Great-Great-Grandnephew) †Muses (Grandnieces/Nieces)Dionysus (Grandnephew)Aecus (Grandnephew) †Minos (Grandnephew) †Rhadamanthus (Grandnephew) †Pollux (Grandnephew) †Peirithous (Grandnephew) †Perseus (Grandnephew) †Hercules (Grandnephew) †Kratos (Grandnephew)Deimos (Grandnephew) †Aeëtes (Grandnephew)Circe (Grandniece)Boreas (Grandnephew) †Nike (Grandniece)Phobos (Great-Grandnephew)Orkos (Great-Grandnephew/Cousin) †Pandora (Adoptive Great-Grandniece) †Zora and Lora (Great-Grandnieces)Asclepius (Great-Grandnephew)Ceryx (Great-Grandnephew/Great-Great-Grandnephew/Great-Great-Great-Grandnephew) †Ariadne (Great-Grandniece/Grandniece-in-Law)Calliope (Great-Grandniece) †Atreus (Great-Grandnephew)Medea (Great-Grandnephew)Jason (Great-Great-Great-Grandnephew/Great-Great-Great-Great-Grandnephew/Great-Great-Great-Great-Great-Grandnephew) †Thanatos (Cousin) †Morpheus (Cousin)Charon (Cousin) †Nemesis (Cousin)Sisters of Fate (Cousins)Erinys (First Cousin Once Removed) †\n\n\n\n\t\n\t\tLoyalties\n\t\n\tGaiaTitans\n\n\n\n\t\n\t\tEnemies\n\t\n\tOlympians\n\n\n\n\n\tBehind the Scenes\n\n\n\t\n\t\tVoiced by\n\t\n\tDee Dee Rescher\n\n\n\n\t\n\t\tAppears in\n\t\n\tGod of War: Ghost of Sparta\n\nThera was a character in God of War: Ghost of Sparta, appearing as an imprisoned lava titaness imprisoned inside the Methana Volcano. She speaks to Kratos during his mission to find his missing brother, Deimos and grants him her power to aid him in his quest, believing that he would help her and the titans.",
  "image": "https://static.wikia.nocookie.net/godofwar/images/7/7e/God_of_War_Ghost_of_Sparta_Playthrough_Part_4_05563.jpg/revision/latest/scale-to-width-down/268?cb=20101025011425",
  "biographicalInformation": {
    "birthplace": "Island of Creation",
    "location": "Methana Volcano outside of Atlantis",
    "status": "Unknown"
  },
  "physicalInformation": {
    "race": "God (Titan)",
    "gender": "Female",
    "hair_colour": "None",
    "skin_colour": "Black"
  },
  "wiki": "https://godofwar.fandom.com/wiki/Thera"
}